stream_remove/code/stream_remove.v
module stream_remove #(
    parameter DATA_WD = 32,           //data数据有多少位
    parameter DATA_BYTE_WD = DATA_WD / 8,   //keep有效位的宽度
    parameter BYTE_CNT_WD = $clog2(DATA_BYTE_WD)   //remove的宽度
) (
    input                         clk,
    input                         rst_n,

    input                         valid_in,
    input [DATA_WD - 1 : 0]       data_in,
    input [DATA_BYTE_WD - 1 : 0]  keep_in, 
    input                         last_in,
    output                        ready_in,

    output                        valid_out,
    output [DATA_WD - 1 : 0]      data_out,  
    output [DATA_BYTE_WD - 1 : 0] keep_out,
    output                        last_out, 
    input                         ready_out,

    input                         valid_remove,
    input [BYTE_CNT_WD - 1 : 0]   byte_remove_cnt,
    output                        ready_remove
);

    localparam DATA_BIT_WD = $clog2(DATA_WD); //data位的宽度

    reg                        valid_in_r;
    reg [DATA_WD - 1 : 0]      data_in_r;
    reg [DATA_BYTE_WD - 1 : 0] keep_in_r;

    wire fire_in = valid_in && ready_in;
    wire fire_out = valid_out && ready_out;
    wire fire_remove = valid_remove && ready_remove;

    reg first_beat_r;
    reg extra_last_beat_r;

    wire [DATA_BYTE_WD - 1 : 0]   keep_nothing = {DATA_BYTE_WD{1'b0}};
    wire [2*DATA_WD - 1 : 0]      double_data = {data_in_r, data_in};
    wire [2*DATA_BYTE_WD - 1 : 0] double_keep = extra_last_beat_r ? 
                                                {keep_in_r , keep_nothing} : 
                                                {keep_in_r, keep_in};

    wire [BYTE_CNT_WD : 0] data_byte_cnt = DATA_BYTE_WD;
    wire [BYTE_CNT_WD : 0] right_shift_byte_cnt = data_byte_cnt - byte_remove_cnt;
    wire [DATA_BIT_WD : 0] right_shift_bit_cnt = right_shift_byte_cnt << 3;

    wire [DATA_BYTE_WD - 1 : 0] next_beat_keep = keep_in << byte_remove_cnt;
    wire                        has_extra_beat = |next_beat_keep;

    assign  data_out = double_data >> right_shift_bit_cnt;
    assign  keep_out = double_keep >> right_shift_byte_cnt;

    assign ready_in = !valid_in_r || (ready_out && valid_remove); // 第一拍的时候/当输出ready并且remove的位数已经valid
    assign valid_out = extra_last_beat_r ? valid_in_r : (valid_in_r && valid_in && valid_remove); // 当有额外最后一拍的时候给到上一拍剩下的valid_r
    assign last_out = extra_last_beat_r || (last_in && !has_extra_beat); // 有额外最后一拍/输入最后一拍并且没用额外下一拍
    assign ready_remove = last_out && fire_out; // 输出最后一拍并且fire时可以更改需要remove的位数，迎接下一个data数据

    //always块再深入理解写一遍
    always @(posedge clk or negedge rst_n) begin
        if(!rst_n) begin
            first_beat_r <= 1'b1;
        end
        else if(fire_in && last_in) begin          //first_beat由输入决定
            first_beat_r <= 1'b1;
        end
        else if(fire_in) begin
            first_beat_r <= 1'b0;
        end
    end                                 //其在fire_in时发生变化，在一个fire周期内保持不变
    
    always @(posedge clk or negedge rst_n) begin
        if(!rst_n) begin
            extra_last_beat_r <= 1'b0;
        end
        else if(fire_in && last_in) begin
            extra_last_beat_r <= has_extra_beat;
        end
        else if(fire_in) begin
            extra_last_beat_r <= 1'b0;
        end
    end

    always @(posedge clk or negedge rst_n) begin
        if(!rst_n) begin
            valid_in_r <= 1'b0;
            data_in_r <= 'b0;
            keep_in_r <= 'b0;
        end
        else begin
            if(fire_out) begin
                valid_in_r <= 1'b0;
            end
            if(fire_in) begin
                valid_in_r <= has_extra_beat;  // valid_in_r要不要拉高取决于下一拍要不要用到这一拍的数据，所以由has_extra_beat决定
                data_in_r <= data_in;
                keep_in_r <= keep_in;
            end
        end
    end

endmodule

stream_remove/code/stream_remove_tb.v
module stream_remove_tb #(
    parameter DATA_WD = 32,
    parameter DATA_BYTE_WD = DATA_WD / 8,
    parameter BYTE_CNT_WD = $clog2(DATA_BYTE_WD)
) ();

    reg                         clk;
    reg                         rst_n;

    reg                         valid_in;
    reg [DATA_WD - 1 : 0]       data_in;
    wire [DATA_BYTE_WD - 1 : 0] keep_in;
    wire                        last_in;
    wire                        ready_in;

    wire                        valid_out;
    wire [DATA_WD - 1 : 0]      data_out;
    wire [DATA_BYTE_WD - 1 : 0] keep_out;
    wire                        last_out;
    reg                         ready_out;

    reg                         valid_remove;
    reg [BYTE_CNT_WD - 1 : 0]   byte_remove_cnt;
    wire                        ready_remove;

    initial begin
        $dumpfile("test.vcd");
        $dumpvars;
    end
    
    initial begin
        clk = 0;
        forever begin
            #5 clk = ~clk;
        end
    end

    initial begin
        rst_n = 0;
        #100
        rst_n = 1;
        #10000
        $finish;
    end

    wire fire_in = valid_in && ready_in;
    wire fire_out = valid_out && ready_out;
    wire fire_remove = valid_remove && ready_remove;
    wire [BYTE_CNT_WD : 0] data_byte_cnt = DATA_BYTE_WD;
    reg first_beat; //首拍，用fire_out && fire_remove的下一拍来赋值

    reg [BYTE_CNT_WD - 1 : 0] last_beat_byte_cnt; //最后一拍无效数据位数
    assign keep_in = last_in ? ~((1 << last_beat_byte_cnt) - 1) : (first_beat ? ((1 << (data_byte_cnt - byte_remove_cnt)) - 1) : ((1 << DATA_BYTE_WD) - 1));

    reg [1 : 0] data_beat_cnt; //第几拍数据
    assign last_in = &data_beat_cnt;

    always @(posedge clk or negedge rst_n) begin
        if(!rst_n) begin
            first_beat <= 1'b0;
        end
        else if (fire_out && fire_remove) begin
            first_beat <= 1'b1;
        end
        else begin
            first_beat <= 1'b0;
        end
    end

    always @(posedge clk or negedge rst_n) begin
        if(!rst_n) begin
            data_in <= 'b0;
        end
        else if(fire_in) begin
            data_in <= $random;
        end
    end

    always @(posedge clk or negedge rst_n) begin
       if(!rst_n) begin
            byte_remove_cnt <= 'b0;
       end
       else if (fire_remove) begin
            byte_remove_cnt <= byte_remove_cnt + 1'b1;
       end 
    end

    always @(posedge clk or negedge rst_n) begin
        if(!rst_n) begin
            data_beat_cnt <= 'b0;
        end
        else begin
            data_beat_cnt <= data_beat_cnt + fire_in;
        end
    end

    always @(posedge clk or negedge rst_n) begin
        if(!rst_n) begin
            last_beat_byte_cnt <= 'b0;      
        end
        else if(fire_out && fire_remove && data_beat_cnt == 2'b11)begin
            last_beat_byte_cnt <= last_beat_byte_cnt + 1'b1;
        end
    end

    localparam RANDOM_FIRE = 0;

    generate if(!RANDOM_FIRE) begin
        always @(posedge clk or negedge rst_n) begin
            if(!rst_n) begin
                valid_in <= 1'b0;  
            end
            else if(!valid_in || ready_in) begin
                valid_in <= 1'b1;
            end
        end
        always @(posedge clk or negedge rst_n) begin
            if(!rst_n) begin
                ready_out <= 1'b1;
                valid_remove <= 1'b0;
            end
            else begin
                ready_out <= 1'b1;
                if(!valid_remove || ready_remove) begin
                    valid_remove <= 1'b1;
                end
            end
        end       
    end
    else begin
        always @(posedge clk or negedge rst_n) begin
            if(!rst_n) begin
                valid_in <= 1'b0;  
            end
            else if(!valid_in || ready_in) begin
                valid_in <= $random;
            end
        end
        always @(posedge clk or negedge rst_n) begin
            if(rst_n) begin
                ready_out <= 1'b1;
                valid_remove <= 1'b0;
            end
            else begin
                ready_out <= $random;
                if(!valid_remove || ready_remove) begin
                    valid_remove <= $random;
                end
            end
        end
    end
        
    endgenerate

    stream_remove #(
        .DATA_WD(DATA_WD),
        .DATA_BYTE_WD(DATA_BYTE_WD),
        .BYTE_CNT_WD(BYTE_CNT_WD)
    ) u_stream_remove (
        .clk(clk),
        .rst_n(rst_n),
        .valid_in(valid_in),
        .data_in(data_in),
        .keep_in(keep_in),
        .last_in(last_in),
        .ready_in(ready_in),
        .valid_out(valid_out),
        .data_out(data_out),
        .keep_out(keep_out),
        .last_out(last_out),
        .ready_out(ready_out),
        .valid_remove(valid_remove),
        .byte_remove_cnt(byte_remove_cnt),
        .ready_remove(ready_remove)
    );

endmodule

stream_remove/sim/test.vcd
$date
	Fri Feb 24 10:48:10 2023
$end
$version
	Icarus Verilog
$end
$timescale
	1s
$end
$scope module stream_remove_tb $end
$var wire 3 ! data_byte_cnt [2:0] $end
$var wire 1 " fire_in $end
$var wire 1 # fire_out $end
$var wire 1 $ fire_remove $end
$var wire 1 % valid_out $end
$var wire 1 & ready_remove $end
$var wire 1 ' ready_in $end
$var wire 1 ( last_out $end
$var wire 1 ) last_in $end
$var wire 4 * keep_out [3:0] $end
$var wire 4 + keep_in [3:0] $end
$var wire 32 , data_out [31:0] $end
$var reg 2 - byte_remove_cnt [1:0] $end
$var reg 1 . clk $end
$var reg 2 / data_beat_cnt [1:0] $end
$var reg 32 0 data_in [31:0] $end
$var reg 1 1 first_beat $end
$var reg 2 2 last_beat_byte_cnt [1:0] $end
$var reg 1 3 ready_out $end
$var reg 1 4 rst_n $end
$var reg 1 5 valid_in $end
$var reg 1 6 valid_remove $end
$scope begin genblk1 $end
$upscope $end
$scope module u_stream_remove $end
$var wire 2 7 byte_remove_cnt [1:0] $end
$var wire 1 . clk $end
$var wire 3 8 data_byte_cnt [2:0] $end
$var wire 32 9 data_in [31:0] $end
$var wire 1 : fire_in $end
$var wire 1 ; fire_out $end
$var wire 1 < fire_remove $end
$var wire 4 = keep_in [3:0] $end
$var wire 2 > keep_nothing [1:0] $end
$var wire 1 ) last_in $end
$var wire 1 ( last_out $end
$var wire 1 ' ready_in $end
$var wire 1 3 ready_out $end
$var wire 1 & ready_remove $end
$var wire 1 4 rst_n $end
$var wire 1 5 valid_in $end
$var wire 1 6 valid_remove $end
$var wire 1 % valid_out $end
$var wire 3 ? right_shift_byte_cnt [2:0] $end
$var wire 6 @ right_shift_bit_cnt [5:0] $end
$var wire 4 A next_beat_keep [3:0] $end
$var wire 4 B keep_out [3:0] $end
$var wire 1 C has_extra_beat $end
$var wire 8 D double_keep [7:0] $end
$var wire 64 E double_data [63:0] $end
$var wire 32 F data_out [31:0] $end
$var reg 32 G data_in_r [31:0] $end
$var reg 1 H extra_last_beat_r $end
$var reg 1 I first_beat_r $end
$var reg 4 J keep_in_r [3:0] $end
$var reg 1 K valid_in_r $end
$upscope $end
$upscope $end
$enddefinitions $end
#0
$dumpvars
0K
b0 J
1I
0H
b0 G
bx F
b0xxxxxxxxxxxxxxxxxxxxxxxxxxxxxxxx E
b0xxxx D
xC
bx B
bx A
bx000 @
bx ?
b0 >
bx =
0<
0;
0:
bx 9
b100 8
bx 7
06
05
04
13
bx 2
x1
bx 0
bx /
0.
bx -
bx ,
bx +
bx *
x)
x(
1'
0&
0%
0$
0#
0"
b100 !
$end
#5
b1111 D
1C
b1111 A
b1111 +
b1111 =
b0 ,
b0 F
0(
b100000 @
b0 *
b0 B
01
b0 E
b0 0
b0 9
b100 ?
b0 -
b0 7
0)
b0 /
b0 2
1.
#10
0.
#15
1.
#20
0.
#25
1.
#30
0.
#35
1.
#40
0.
#45
1.
#50
0.
#55
1.
#60
0.
#65
1.
#70
0.
#75
1.
#80
0.
#85
1.
#90
0.
#95
1.
#100
0.
14
#105
1:
1"
16
15
1.
#110
0.
#115
1;
1#
1%
b1111 *
b1111 B
b11111111 D
0I
b1111 J
1K
b1 /
b10010000101010011010100100100 E
b10010000101010011010100100100 0
b10010000101010011010100100100 9
1.
#120
0.
#125
b10010000101010011010100100100 ,
b10010000101010011010100100100 F
b11000000100010010101111010000001 0
b11000000100010010101111010000001 9
b10 /
b1001000010101001101010010010011000000100010010101111010000001 E
b10010000101010011010100100100 G
1K
1.
#130
0.
#135
b11000000100010010101111010000001 ,
b11000000100010010101111010000001 F
b11000000100010010101111010000001 G
1K
1)
b11 /
b1100000010001001010111101000000110000100100001001101011000001001 E
b10000100100001001101011000001001 0
b10000100100001001101011000001001 9
1.
#140
0.
#145
1<
1$
b11 *
b11 B
1&
b10000100100001001101011000001001 ,
b10000100100001001101011000001001 F
b111100 D
1(
b10110001111100000101011001100011 0
b10110001111100000101011001100011 9
0)
b0 /
b1000010010000100110101100000100110110001111100000101011001100011 E
b10000100100001001101011000001001 G
1K
1H
1I
1.
#150
0.
#155
0<
0$
0&
b111 +
b111 =
b11110111 D
0(
b11110000010101100110001100000110 ,
b11110000010101100110001100000110 F
b11000 @
b1110 *
b1110 B
0I
0H
b10110001111100000101011001100011 G
1K
b1 /
b11 ?
b1110 A
b1 -
b1 7
b1011000111110000010101100110001100000110101110010111101100001101 E
b110101110010111101100001101 0
b110101110010111101100001101 9
11
1.
#160
0.
#165
b1111 *
b1111 B
b1111 +
b1111 =
b1111111 D
b10111001011110110000110101000110 ,
b10111001011110110000110101000110 F
01
b1000110110111111001100110001101 0
b1000110110111111001100110001101 9
b10 /
b111 J
b11010111001011110110000110101000110110111111001100110001101 E
b110101110010111101100001101 G
1K
1.
#170
0.
#175
b11111111 D
b11011111100110011000110110110010 ,
b11011111100110011000110110110010 F
b1111 J
b1000110110111111001100110001101 G
1K
1)
b11 /
b100011011011111100110011000110110110010110000101000010001100101 E
b10110010110000101000010001100101 0
b10110010110000101000010001100101 9
1.
#180
0.
#185
1<
1$
b111 *
b111 B
1&
b11000010100001000110010110001001 ,
b11000010100001000110010110001001 F
b111100 D
1(
b10001001001101110101001000010010 0
b10001001001101110101001000010010 9
0)
b0 /
b1011001011000010100001000110010110001001001101110101001000010010 E
b10110010110000101000010001100101 G
1K
1H
1I
1.
#190
0.
#195
0<
0$
0&
b11 +
b11 =
b11110011 D
0(
b10000 @
b1100 *
b1100 B
b1010010000100100000000011110011 ,
b1010010000100100000000011110011 F
0I
0H
b10001001001101110101001000010010 G
1K
b1 /
b10 ?
b1100 A
b10 -
b10 7
b1000100100110111010100100001001000000000111100111110001100000001 E
b111100111110001100000001 0
b111100111110001100000001 9
11
1.
#200
0.
#205
b1111 *
b1111 B
b1111 +
b1111 =
b111111 D
b11100011000000010000011011010111 ,
b11100011000000010000011011010111 F
01
b110110101111100110100001101 0
b110110101111100110100001101 9
b10 /
b11 J
b11110011111000110000000100000110110101111100110100001101 E
b111100111110001100000001 G
1K
1.
#210
0.
#215
b11111111 D
b11001101000011010011101100100011 ,
b11001101000011010011101100100011 F
b1111 J
b110110101111100110100001101 G
1K
1)
b11 /
b11011010111110011010000110100111011001000111111000101110110 E
b111011001000111111000101110110 0
b111011001000111111000101110110 9
1.
#220
0.
#225
1<
1$
1&
b11110001011101100001111010001101 ,
b11110001011101100001111010001101 F
b111100 D
1(
b11110100011011100110100111101 0
b11110100011011100110100111101 9
0)
b0 /
b11101100100011111100010111011000011110100011011100110100111101 E
b111011001000111111000101110110 G
1K
1H
1I
1.
#230
0.
#235
0<
0$
0&
b1 +
b1 =
b11110001 D
0(
b1000 @
b1000 *
b1000 B
b111101011101101101010001010111 ,
b111101011101101101010001010111 F
0I
0H
b11110100011011100110100111101 G
1K
b1 /
b1 ?
b1000 A
b11 -
b11 7
b1111010001101110011010011110101110110110101000101011111101101 E
b1110110110101000101011111101101 0
b1110110110101000101011111101101 9
11
1.
#240
0.
#245
b1111 *
b1111 B
b1111 +
b1111 =
b11111 D
b11101101010001100010110111110111 ,
b11101101010001100010110111110111 F
01
b1000110001011011111011110001100 0
b1000110001011011111011110001100 9
b10 /
b1 J
b111011011010100010101111110110101000110001011011111011110001100 E
b1110110110101000101011111101101 G
1K
1.
#250
0.
#255
b11111111 D
b10001100011111001111110111101001 ,
b10001100011111001111110111101001 F
b1111 J
b1000110001011011111011110001100 G
1K
1)
b11 /
b100011000101101111101111000110001111100111111011110100111111001 E
b1111100111111011110100111111001 0
b1111100111111011110100111111001 9
1.
#260
0.
#265
1<
1$
b1110 *
b1110 B
1&
b11111001111000110011011100100100 ,
b11111001111000110011011100100100 F
b111100 D
1(
b11100011001101110010010011000110 0
b11100011001101110010010011000110 9
0)
b0 /
b111110011111101111010011111100111100011001101110010010011000110 E
b1111100111111011110100111111001 G
1K
1H
1I
1.
#270
0.
#275
0<
0$
0&
b11111111 D
0(
b100000 @
b1111 *
b1111 B
b11100011001101110010010011000110 ,
b11100011001101110010010011000110 F
0I
0H
b11100011001101110010010011000110 G
1K
b1 /
b100 ?
b1111 A
b0 -
b0 7
b1110001100110111001001001100011011100010111101111000010011000101 E
b11100010111101111000010011000101 0
b11100010111101111000010011000101 9
11
1.
#280
0.
#285
b11100010111101111000010011000101 ,
b11100010111101111000010011000101 F
01
b11010101000100111101001010101010 0
b11010101000100111101001010101010 9
b10 /
b1110001011110111100001001100010111010101000100111101001010101010 E
b11100010111101111000010011000101 G
1K
1.
#290
0.
#295
b11010101000100111101001010101010 ,
b11010101000100111101001010101010 F
b11010101000100111101001010101010 G
1K
1)
b11 /
b1101010100010011110100101010101001110010101011111111011111100101 E
b1110010101011111111011111100101 0
b1110010101011111111011111100101 9
1.
#300
0.
#305
1<
1$
b11 *
b11 B
1&
b1110010101011111111011111100101 ,
b1110010101011111111011111100101 F
b111100 D
1(
b10111011110100100111001001110111 0
b10111011110100100111001001110111 9
0)
b0 /
b111001010101111111101111110010110111011110100100111001001110111 E
b1110010101011111111011111100101 G
1K
1H
1I
1.
#310
0.
#315
0<
0$
0&
b111 +
b111 =
b11110111 D
0(
b11010010011100100111011110001001 ,
b11010010011100100111011110001001 F
b11000 @
b1110 *
b1110 B
0I
0H
b10111011110100100111001001110111 G
1K
b1 /
b11 ?
b1110 A
b1 -
b1 7
b1011101111010010011100100111011110001001001100101101011000010010 E
b10001001001100101101011000010010 0
b10001001001100101101011000010010 9
11
1.
#320
0.
#325
b1111 *
b1111 B
b1111 +
b1111 =
b1111111 D
b110010110101100001001001000111 ,
b110010110101100001001001000111 F
01
b1000111111011001101101110001111 0
b1000111111011001101101110001111 9
b10 /
b111 J
b1000100100110010110101100001001001000111111011001101101110001111 E
b10001001001100101101011000010010 G
1K
1.
#330
0.
#335
b11111111 D
b11101100110110111000111101111001 ,
b11101100110110111000111101111001 F
b1111 J
b1000111111011001101101110001111 G
1K
1)
b11 /
b100011111101100110110111000111101111001001100000110100111110010 E
b1111001001100000110100111110010 0
b1111001001100000110100111110010 9
1.
#340
0.
#345
1<
1$
b111 *
b111 B
1&
b110000011010011111001011100111 ,
b110000011010011111001011100111 F
b111100 D
1(
b11100111011101101001011011001110 0
b11100111011101101001011011001110 9
0)
b0 /
b111100100110000011010011111001011100111011101101001011011001110 E
b1111001001100000110100111110010 G
1K
1H
1I
1.
#350
0.
#355
0<
0$
0&
b11 +
b11 =
b11110011 D
0(
b10000 @
b1100 *
b1100 B
b10010110110011101111010000000000 ,
b10010110110011101111010000000000 F
0I
0H
b11100111011101101001011011001110 G
1K
b1 /
b10 ?
b1100 A
b10 -
b10 7
b1110011101110110100101101100111011110100000000000111101011101000 E
b11110100000000000111101011101000 0
b11110100000000000111101011101000 9
11
1.
#360
0.
#365
b1111 *
b1111 B
b1111 +
b1111 =
b111111 D
b1111010111010001110001011001010 ,
b1111010111010001110001011001010 F
01
b11100010110010100100111011000101 0
b11100010110010100100111011000101 9
b10 /
b11 J
b1111010000000000011110101110100011100010110010100100111011000101 E
b11110100000000000111101011101000 G
1K
1.
#370
0.
#375
b11111111 D
b1001110110001010010111001011000 ,
b1001110110001010010111001011000 F
b1111 J
b11100010110010100100111011000101 G
1K
1)
b11 /
b1110001011001010010011101100010100101110010110000100100101011100 E
b101110010110000100100101011100 0
b101110010110000100100101011100 9
1.
#380
0.
#385
1<
1$
1&
b1001001010111001101111010001110 ,
b1001001010111001101111010001110 F
b111100 D
1(
b11011110100011100010100010111101 0
b11011110100011100010100010111101 9
0)
b0 /
b10111001011000010010010101110011011110100011100010100010111101 E
b101110010110000100100101011100 G
1K
1H
1I
1.
#390
0.
#395
0<
0$
0&
b1 +
b1 =
b11110001 D
0(
b1000 @
b1000 *
b1000 B
b10111101100101101010101101011000 ,
b10111101100101101010101101011000 F
0I
0H
b11011110100011100010100010111101 G
1K
b1 /
b1 ?
b1000 A
b11 -
b11 7
b1101111010001110001010001011110110010110101010110101100000101101 E
b10010110101010110101100000101101 0
b10010110101010110101100000101101 9
11
1.
#400
0.
#405
b1111 *
b1111 B
b1111 +
b1111 =
b11111 D
b101101101100101010011100100110 ,
b101101101100101010011100100110 F
01
b10110010101001110010011001100101 0
b10110010101001110010011001100101 9
b10 /
b1 J
b1001011010101011010110000010110110110010101001110010011001100101 E
b10010110101010110101100000101101 G
1K
1.
#410
0.
#415
b11111111 D
b1100101101100011110111101100010 ,
b1100101101100011110111101100010 F
b1111 J
b10110010101001110010011001100101 G
1K
1)
b11 /
b1011001010100111001001100110010110110001111011110110001001100011 E
b10110001111011110110001001100011 0
b10110001111011110110001001100011 9
1.
#420
0.
#425
1<
1$
b1110 *
b1110 B
1&
b1100011000001010111001110000111 ,
b1100011000001010111001110000111 F
b111100 D
1(
b101011100111000011100001010 0
b101011100111000011100001010 9
0)
b0 /
b1011000111101111011000100110001100000101011100111000011100001010 E
b10110001111011110110001001100011 G
1K
1H
1I
1.
#430
0.
#435
0<
0$
0&
b11111111 D
0(
b100000 @
b1111 *
b1111 B
b101011100111000011100001010 ,
b101011100111000011100001010 F
0I
0H
b101011100111000011100001010 G
1K
b1 /
b100 ?
b1111 A
b0 -
b0 7
b10101110011100001110000101011000000001110110010001010000000 E
b11000000001110110010001010000000 0
b11000000001110110010001010000000 9
11
1.
#440
0.
#445
b11000000001110110010001010000000 ,
b11000000001110110010001010000000 F
01
b10000011001000010000100100000 0
b10000011001000010000100100000 9
b10 /
b1100000000111011001000101000000000010000011001000010000100100000 E
b11000000001110110010001010000000 G
1K
1.
#450
0.
#455
b10000011001000010000100100000 ,
b10000011001000010000100100000 F
b10000011001000010000100100000 G
1K
1)
b11 /
b1000001100100001000010010000001010101011110000100010110101010 E
b1010101011110000100010110101010 0
b1010101011110000100010110101010 9
1.
#460
0.
#465
1<
1$
b11 *
b11 B
1&
b1010101011110000100010110101010 ,
b1010101011110000100010110101010 F
b111100 D
1(
b11001110110011001100110010011101 0
b11001110110011001100110010011101 9
0)
b0 /
b101010101111000010001011010101011001110110011001100110010011101 E
b1010101011110000100010110101010 G
1K
1H
1I
1.
#470
0.
#475
0<
0$
0&
b111 +
b111 =
b11110111 D
0(
b11001100110011001001110111001011 ,
b11001100110011001001110111001011 F
b11000 @
b1110 *
b1110 B
0I
0H
b11001110110011001100110010011101 G
1K
b1 /
b11 ?
b1110 A
b1 -
b1 7
b1100111011001100110011001001110111001011001000000011111010010110 E
b11001011001000000011111010010110 0
b11001011001000000011111010010110 9
11
1.
#480
0.
#485
b1111 *
b1111 B
b1111 +
b1111 =
b1111111 D
b100000001111101001011010001001 ,
b100000001111101001011010001001 F
01
b10001001100000111011100000010011 0
b10001001100000111011100000010011 9
b10 /
b111 J
b1100101100100000001111101001011010001001100000111011100000010011 E
b11001011001000000011111010010110 G
1K
1.
#490
0.
#495
b11111111 D
b10000011101110000001001110000110 ,
b10000011101110000001001110000110 F
b1111 J
b10001001100000111011100000010011 G
1K
1)
b11 /
b1000100110000011101110000001001110000110101111000011100000001101 E
b10000110101111000011100000001101 0
b10000110101111000011100000001101 9
1.
#500
0.
#505
1<
1$
b111 *
b111 B
1&
b10111100001110000000110110101001 ,
b10111100001110000000110110101001 F
b111100 D
1(
b10101001101001111101011001010011 0
b10101001101001111101011001010011 9
0)
b0 /
b1000011010111100001110000000110110101001101001111101011001010011 E
b10000110101111000011100000001101 G
1K
1H
1I
1.
#510
0.
#515
0<
0$
0&
b11 +
b11 =
b11110011 D
0(
b10000 @
b1100 *
b1100 B
b11010110010100110011010110011111 ,
b11010110010100110011010110011111 F
0I
0H
b10101001101001111101011001010011 G
1K
b1 /
b10 ?
b1100 A
b10 -
b10 7
b1010100110100111110101100101001100110101100111111101110101101011 E
b110101100111111101110101101011 0
b110101100111111101110101101011 9
11
1.
#520
0.
#525
b1111 *
b1111 B
b1111 +
b1111 =
b111111 D
b11011101011010111110101010100110 ,
b11011101011010111110101010100110 F
01
b11101010101001100010101011010101 0
b11101010101001100010101011010101 9
b10 /
b11 J
b11010110011111110111010110101111101010101001100010101011010101 E
b110101100111111101110101101011 G
1K
1.
#530
0.
#535
b11111111 D
b101010110101011000000100010111 ,
b101010110101011000000100010111 F
b1111 J
b11101010101001100010101011010101 G
1K
1)
b11 /
b1110101010100110001010101101010110000001000101110100101000000010 E
b10000001000101110100101000000010 0
b10000001000101110100101000000010 9
1.
#540
0.
#545
1<
1$
1&
b1001010000000101101011101010110 ,
b1001010000000101101011101010110 F
b111100 D
1(
b11010111010101100011111010101110 0
b11010111010101100011111010101110 9
0)
b0 /
b1000000100010111010010100000001011010111010101100011111010101110 E
b10000001000101110100101000000010 G
1K
1H
1I
1.
#550
0.
#555
0<
0$
0&
b1 +
b1 =
b11110001 D
0(
b1000 @
b1000 *
b1000 B
b10101110000011101111111111101001 ,
b10101110000011101111111111101001 F
0I
0H
b11010111010101100011111010101110 G
1K
b1 /
b1 ?
b1000 A
b11 -
b11 7
b1101011101010110001111101010111000001110111111111110100100011101 E
b1110111111111110100100011101 0
b1110111111111110100100011101 9
11
1.
#560
0.
#565
b1111 *
b1111 B
b1111 +
b1111 =
b11111 D
b11101111001111100010101110010 ,
b11101111001111100010101110010 F
01
b11100111110001010111001011001111 0
b11100111110001010111001011001111 9
b10 /
b1 J
b111011111111111010010001110111100111110001010111001011001111 E
b1110111111111110100100011101 G
1K
1.
#570
0.
#575
b11111111 D
b11001111000100011000010001001001 ,
b11001111000100011000010001001001 F
b1111 J
b11100111110001010111001011001111 G
1K
1)
b11 /
b1110011111000101011100101100111100010001100001000100100100100011 E
b10001100001000100100100100011 0
b10001100001000100100100100011 9
1.
#580
0.
#585
1<
1$
b1110 *
b1110 B
1&
b100011000001010000100101100101 ,
b100011000001010000100101100101 F
b111100 D
1(
b101000010010110010100001010 0
b101000010010110010100001010 9
0)
b0 /
b1000110000100010010010010001100000101000010010110010100001010 E
b10001100001000100100100100011 G
1K
1H
1I
1.
#590
0.
#595
0<
0$
0&
b11111111 D
0(
b100000 @
b1111 *
b1111 B
b101000010010110010100001010 ,
b101000010010110010100001010 F
0I
0H
b101000010010110010100001010 G
1K
b1 /
b100 ?
b1111 A
b0 -
b0 7
b10100001001011001010000101011100101011100110000101011001010 E
b11100101011100110000101011001010 0
b11100101011100110000101011001010 9
11
1.
#600
0.
#605
b11100101011100110000101011001010 ,
b11100101011100110000101011001010 F
01
b10011110001100010100110000111100 0
b10011110001100010100110000111100 9
b10 /
b1110010101110011000010101100101010011110001100010100110000111100 E
b11100101011100110000101011001010 G
1K
1.
#610
0.
#615
b10011110001100010100110000111100 ,
b10011110001100010100110000111100 F
b10011110001100010100110000111100 G
1K
1)
b11 /
b1001111000110001010011000011110001111001011010001011110111110010 E
b1111001011010001011110111110010 0
b1111001011010001011110111110010 9
1.
#620
0.
#625
1<
1$
b11 *
b11 B
1&
b1111001011010001011110111110010 ,
b1111001011010001011110111110010 F
b111100 D
1(
b1000101001011100110000110001010 0
b1000101001011100110000110001010 9
0)
b0 /
b111100101101000101111011111001001000101001011100110000110001010 E
b1111001011010001011110111110010 G
1K
1H
1I
1.
#630
0.
#635
0<
0$
0&
b111 +
b111 =
b11110111 D
0(
b101110011000011000101000100000 ,
b101110011000011000101000100000 F
b11000 @
b1110 *
b1110 B
0I
0H
b1000101001011100110000110001010 G
1K
b1 /
b11 ?
b1110 A
b1 -
b1 7
b100010100101110011000011000101000100000110001001011001101000001 E
b100000110001001011001101000001 0
b100000110001001011001101000001 9
11
1.
#640
0.
#645
b1111 *
b1111 B
b1111 +
b1111 =
b1111111 D
b11000100101100110100000111101100 ,
b11000100101100110100000111101100 F
01
b11101100010010110011010011011000 0
b11101100010010110011010011011000 9
b10 /
b111 J
b10000011000100101100110100000111101100010010110011010011011000 E
b100000110001001011001101000001 G
1K
1.
#650
0.
#655
b11111111 D
b1001011001101001101100000111100 ,
b1001011001101001101100000111100 F
b1111 J
b11101100010010110011010011011000 G
1K
1)
b11 /
b1110110001001011001101001101100000111100001000001111001101111000 E
b111100001000001111001101111000 0
b111100001000001111001101111000 9
1.
#660
0.
#665
1<
1$
b111 *
b111 B
1&
b100000111100110111100011000100 ,
b100000111100110111100011000100 F
b111100 D
1(
b11000100100010100001001010001001 0
b11000100100010100001001010001001 9
0)
b0 /
b11110000100000111100110111100011000100100010100001001010001001 E
b111100001000001111001101111000 G
1K
1H
1I
1.
#670
0.
#675
0<
0$
0&
b11 +
b11 =
b11110011 D
0(
b10000 @
b1100 *
b1100 B
b10010100010010111010111000101 ,
b10010100010010111010111000101 F
0I
0H
b11000100100010100001001010001001 G
1K
b1 /
b10 ?
b1100 A
b10 -
b10 7
b1100010010001010000100101000100101110101110001010000110111101011 E
b1110101110001010000110111101011 0
b1110101110001010000110111101011 9
11
1.
#680
0.
#685
b1111 *
b1111 B
b1111 +
b1111 =
b111111 D
b1101111010110101101100000010 ,
b1101111010110101101100000010 F
01
b1011011000000100110010110110110 0
b1011011000000100110010110110110 9
b10 /
b11 J
b111010111000101000011011110101101011011000000100110010110110110 E
b1110101110001010000110111101011 G
1K
1.
#690
0.
#695
b11111111 D
b1100101101101100110001101001011 ,
b1100101101101100110001101001011 F
b1111 J
b1011011000000100110010110110110 G
1K
1)
b11 /
b101101100000010011001011011011001100011010010111111100111000110 E
b1100011010010111111100111000110 0
b1100011010010111111100111000110 9
1.
#700
0.
#705
1<
1$
1&
b11111001110001100101011100010101 ,
b11111001110001100101011100010101 F
b111100 D
1(
b1010111000101010001001110101110 0
b1010111000101010001001110101110 9
0)
b0 /
b110001101001011111110011100011001010111000101010001001110101110 E
b1100011010010111111100111000110 G
1K
1H
1I
1.
#710
0.
#715
0<
0$
0&
b1 +
b1 =
b11110001 D
0(
b1000 @
b1000 *
b1000 B
b10101110110111100111010100000010 ,
b10101110110111100111010100000010 F
0I
0H
b1010111000101010001001110101110 G
1K
b1 /
b1 ?
b1000 A
b11 -
b11 7
b101011100010101000100111010111011011110011101010000001010111100 E
b11011110011101010000001010111100 0
b11011110011101010000001010111100 9
11
1.
#720
0.
