stream_insert/code/stream_insert.v
module stream_insert #(
    parameter DATA_WD = 32,
    parameter DATA_BYTE_WD = DATA_WD / 8,
    parameter BYTE_CNT_WD = $clog2(DATA_BYTE_WD)
) (
    input                         clk,
    input                         rst_n,

    input                         valid_in,
    input [DATA_BYTE_WD - 1 : 0]  keep_in,
    input [DATA_WD - 1 : 0]       data_in,
    input                         last_in,
    output                        ready_in,

    output                        valid_out,
    output [DATA_BYTE_WD - 1 : 0] keep_out,
    output [DATA_WD - 1 : 0]      data_out,
    output                        last_out,
    input                         ready_out,

    input                         valid_insert,
    input [BYTE_CNT_WD - 1 : 0]   byte_insert_cnt,
    input [DATA_WD - 1 : 0]       data_insert,
    input [BYTE_CNT_WD - 1 : 0]   keep_insert,        
    output                        ready_insert
);

    localparam DATA_BIT_CNT_WD = $clog2(DATA_WD); //用于给double_data右移数据量提供宽度

    wire fire_in     = valid_in && ready_in;
    wire fire_out    = valid_out && ready_out;
    wire fire_insert = valid_insert && ready_insert;

    reg                        valid_in_r;
    reg [DATA_WD - 1 : 0]      data_in_r;
    reg [DATA_BYTE_WD - 1 : 0] keep_in_r;

    reg first_beat_r;
    reg extra_last_beat_r;

    wire [DATA_BYTE_WD - 1 : 0] keep_nothing = {DATA_BYTE_WD{1'b0}};

    wire [2*DATA_WD - 1 : 0]      double_data = first_beat_r ? {data_insert , data_in} : {data_in_r , data_in};
    wire [2*DATA_BYTE_WD - 1 : 0] double_keep = first_beat_r ?
                                                {keep_insert , keep_in} : 
                                                (extra_last_beat_r ?
                                                {keep_in_r , keep_nothing} : {keep_in_r , keep_in}
                                                );

    wire [BYTE_CNT_WD - 1     : 0] right_shift_byte_cnt = byte_insert_cnt;
    wire [DATA_BIT_CNT_WD - 1 : 0] right_shift_bit_cnt  = right_shift_byte_cnt << 3;
    
    assign data_out = double_data >> right_shift_bit_cnt;
    assign keep_out = double_keep >> right_shift_byte_cnt;

    wire [BYTE_CNT_WD : 0]      data_byte_cnt       = DATA_BYTE_WD;
    wire [BYTE_CNT_WD - 1 : 0]  lift_shift_byte_cnt = data_byte_cnt - byte_insert_cnt;
    wire [DATA_BYTE_WD - 1 : 0] next_byte_to_keep   = keep_in << lift_shift_byte_cnt;
    wire                        has_extra_beat      = !extra_last_beat_r && |next_byte_to_keep;
    
    assign ready_insert = fire_out && last_out;
    assign ready_in     = first_beat_r || (ready_out && valid_insert && !extra_last_beat_r);
    assign valid_out    = first_beat_r ? 
                        valid_in : 
                        (extra_last_beat_r ?
                         valid_in_r :
                         (valid_in && valid_in_r)
                        )&& valid_insert; //特别注意首拍和最后一拍                        
    assign last_out     = extra_last_beat_r || (last_in && !has_extra_beat);  //不是fire_out && !has_extra_beat，是last_in，想象有一条线直通

    always @(posedge clk or negedge rst_n) begin
        if(!rst_n) begin
            first_beat_r <= 1'b1;            
        end
        else if(last_out && fire_out ) begin
            first_beat_r <= 1'b1;                 //stream_remove是用输入fire_in来控制，而stream_insert不行
        end                                       //为什么？
        else if(fire_out) begin
            first_beat_r <= 1'b0;
        end
    end

    always @(posedge clk or negedge rst_n) begin
        if(!rst_n) begin
            extra_last_beat_r <= 1'b0;
        end
        else if (has_extra_beat && last_in && fire_in) begin
            extra_last_beat_r <= 1'b1;
        end
        else if (fire_out) begin
            extra_last_beat_r <= 1'b0;
        end
    end

    always @(posedge clk or negedge rst_n) begin
        if(!rst_n) begin
            valid_in_r <= 1'b0;
            data_in_r  <= 'b0;
            keep_in_r  <= 'b0;
        end
        else begin
            if(fire_out) begin
                valid_in_r <= 1'b0;
            end
            if (fire_in) begin      //不能&&fire_insert，因为规定insert数据在一组数据传输完才发生变化，然而fire_in会fire多次
                valid_in_r <= valid_in;
                data_in_r  <= data_in;
                keep_in_r  <= keep_in;
        end
        end
    end

endmodule

stream_insert/code/stream_insert_tb.v
module stream_insert_tb #(
    parameter DATA_WD = 32,
    parameter DATA_BYTE_WD = DATA_WD / 8,
    parameter BYTE_CNT_WD = $clog2(DATA_BYTE_WD)
)();

    reg                           clk;
    reg                         rst_n;

    reg                         valid_in;
    wire [DATA_BYTE_WD - 1 : 0] keep_in;
    reg [DATA_WD - 1 : 0]       data_in;
    wire                        last_in;
    wire                        ready_in;

    wire                        valid_out;
    wire [DATA_BYTE_WD - 1 : 0] keep_out;
    wire [DATA_WD - 1 : 0]      data_out;
    wire                        last_out;
    reg                         ready_out;

    reg                         valid_insert;
    reg [BYTE_CNT_WD - 1 : 0]   byte_insert_cnt;
    reg [DATA_WD - 1 : 0]       data_insert;
    wire [BYTE_CNT_WD - 1 : 0]  keep_insert;        
    wire                        ready_insert;

    initial begin
        clk = 0;
        forever begin
            #5 clk = ~clk;
        end
    end

    initial begin
        rst_n = 0;
        #100
        rst_n = 1;
        #10000
        $finish;
    end

    initial begin
        $dumpfile("test.vcd");
        $dumpvars;
    end

    reg [BYTE_CNT_WD - 1 : 0] data_input_beat_cnt;
    reg [BYTE_CNT_WD - 1 : 0] last_beat_invalid_byte;

    assign keep_in = last_in ? ~((1 << last_beat_invalid_byte) - 1) : ((1 << DATA_BYTE_WD) - 1);
    assign last_in = &data_input_beat_cnt;
    assign keep_insert = (1 << byte_insert_cnt) - 1;

    wire fire_in     = valid_in && ready_in;
    wire fire_out    = valid_out && ready_out;
    wire fire_insert = valid_insert && ready_insert;

    always @(posedge clk or negedge rst_n) begin
        if(!rst_n) begin
            data_insert            <= 'b0;
            byte_insert_cnt        <= 'b0;
            last_beat_invalid_byte <= 'b0;    
        end
        else if(fire_insert) begin // fire_out && last_out是ready_insert，而不一定valid
            data_insert <= $random;
            byte_insert_cnt <= byte_insert_cnt + 1'b1;
            if (&byte_insert_cnt) begin
                last_beat_invalid_byte <= last_beat_invalid_byte + 1'b1;
                if(last_beat_invalid_byte == DATA_BYTE_WD - 1) begin
                    last_beat_invalid_byte <= 'b0;                    //注意清零，但是感觉不清零也可以？因为有位数限制
                end
            end
        end
    end
//也可以data_insert和data_in一起处理，byte_insert_cnt和last_beat一起处理

    always @(posedge clk or negedge rst_n) begin
        if(!rst_n) begin
            data_input_beat_cnt <= 'b0;
        end
        else if (fire_in) begin
            data_input_beat_cnt <= data_input_beat_cnt + 1'b1;  //注意是input的beat,所以fire_in触发
        end
    end

    always @(posedge clk or negedge rst_n) begin
        if(!rst_n) begin
            data_in <= 'b0;
        end
        else if(fire_in) begin
            data_in <= $random;
        end
    end

    localparam RANDOM_FIRE = 0;
    generate if(!RANDOM_FIRE) begin
        always @(posedge clk or negedge rst_n) begin
            if(!rst_n) begin
                valid_in     <= 1'b0;
                ready_out    <= 1'b1;
                valid_insert <= 1'b0;
            end
            else begin
                valid_in     <= 1'b1;
                ready_out    <= 1'b1;
                valid_insert <= 1'b1;
            end
        end
    end
    else begin
        always @(posedge clk or negedge rst_n) begin
            if(!rst_n) begin
                valid_in     <= 1'b0;
                ready_out    <= 1'b1;
                valid_insert <= 1'b0;
            end
            else begin     //注意只有在has_not_pending的时候才可以改变valid数据!!!
                ready_out <= $random;
                if(!valid_in || ready_in) begin
                    valid_in <= $random;
                end
                if(!valid_insert || ready_insert) begin
                    valid_insert <= $random;
                end
            end
            end
        end
    endgenerate
    
//valid和ready信号在最后一个always块里集中处理

    stream_insert #(
        .DATA_WD(DATA_WD),
        .DATA_BYTE_WD(DATA_BYTE_WD),
        .BYTE_CNT_WD(BYTE_CNT_WD)
    ) u_stream_insert (
        .clk(clk),
        .rst_n(rst_n),
        .valid_in(valid_in),
        .keep_in(keep_in),
        .data_in(data_in),
        .last_in(last_in),
        .ready_in(ready_in),
        .valid_out(valid_out),
        .keep_out(keep_out),
        .data_out(data_out),
        .last_out(last_out),
        .ready_out(ready_out),
        .valid_insert(valid_insert),
        .keep_insert(keep_insert),
        .data_insert(data_insert),
        .byte_insert_cnt(byte_insert_cnt),
        .ready_insert(ready_insert)
    );

endmodule

stream_insert/sim/test.vcd
$date
	Mon Feb 27 10:35:27 2023
$end
$version
	Icarus Verilog
$end
$timescale
	1s
$end
$scope module stream_insert_tb $end
$var wire 1 ! fire_in $end
$var wire 1 " fire_insert $end
$var wire 1 # fire_out $end
$var wire 1 $ valid_out $end
$var wire 1 % ready_insert $end
$var wire 1 & ready_in $end
$var wire 1 ' last_out $end
$var wire 1 ( last_in $end
$var wire 4 ) keep_out [3:0] $end
$var wire 2 * keep_insert [1:0] $end
$var wire 4 + keep_in [3:0] $end
$var wire 32 , data_out [31:0] $end
$var reg 2 - byte_insert_cnt [1:0] $end
$var reg 1 . clk $end
$var reg 32 / data_in [31:0] $end
$var reg 2 0 data_input_beat_cnt [1:0] $end
$var reg 32 1 data_insert [31:0] $end
$var reg 2 2 last_beat_invalid_byte [1:0] $end
$var reg 1 3 ready_out $end
$var reg 1 4 rst_n $end
$var reg 1 5 valid_in $end
$var reg 1 6 valid_insert $end
$scope begin genblk1 $end
$upscope $end
$scope module u_stream_insert $end
$var wire 2 7 byte_insert_cnt [1:0] $end
$var wire 1 . clk $end
$var wire 3 8 data_byte_cnt [2:0] $end
$var wire 32 9 data_in [31:0] $end
$var wire 32 : data_insert [31:0] $end
$var wire 1 ; fire_in $end
$var wire 1 < fire_insert $end
$var wire 1 = fire_out $end
$var wire 1 > has_extra_beat $end
$var wire 4 ? keep_in [3:0] $end
$var wire 2 @ keep_insert [1:0] $end
$var wire 4 A keep_nothing [3:0] $end
$var wire 1 ( last_in $end
$var wire 1 ' last_out $end
$var wire 1 & ready_in $end
$var wire 1 % ready_insert $end
$var wire 1 3 ready_out $end
$var wire 2 B right_shift_byte_cnt [1:0] $end
$var wire 1 4 rst_n $end
$var wire 1 5 valid_in $end
$var wire 1 6 valid_insert $end
$var wire 1 $ valid_out $end
$var wire 5 C right_shift_bit_cnt [4:0] $end
$var wire 4 D next_byte_to_keep [3:0] $end
$var wire 2 E lift_shift_byte_cnt [1:0] $end
$var wire 4 F keep_out [3:0] $end
$var wire 8 G double_keep [7:0] $end
$var wire 64 H double_data [63:0] $end
$var wire 32 I data_out [31:0] $end
$var reg 32 J data_in_r [31:0] $end
$var reg 1 K extra_last_beat_r $end
$var reg 1 L first_beat_r $end
$var reg 4 M keep_in_r [3:0] $end
$var reg 1 N valid_in_r $end
$upscope $end
$upscope $end
$enddefinitions $end
#0
$dumpvars
0N
b0 M
1L
0K
b0 J
bx I
bx H
b0xxxxxx G
bx F
bx E
bx D
bx000 C
bx B
b0 A
bx @
bx ?
x>
0=
0<
0;
bx :
bx 9
b100 8
bx 7
06
05
04
13
bx 2
bx 1
bx 0
bx /
0.
bx -
bx ,
bx +
bx *
bx )
x(
x'
1&
0%
0$
0#
0"
0!
$end
#5
b1111 )
b1111 F
b0 ,
b0 I
1>
0'
b1111 G
b0 C
b1111 D
b0 E
b1111 +
b1111 ?
b0 H
b0 2
b0 *
b0 @
b0 B
b0 -
b0 7
b0 1
b0 :
0(
b0 0
b0 /
b0 9
1.
#10
0.
#15
1.
#20
0.
#25
1.
#30
0.
#35
1.
#40
0.
#45
1.
#50
0.
#55
1.
#60
0.
#65
1.
#70
0.
#75
1.
#80
0.
#85
1.
#90
0.
#95
1.
#100
0.
14
#105
1=
1#
1;
1$
1!
16
15
1.
#110
0.
#115
1=
1#
b10010000101010011010100100100 ,
b10010000101010011010100100100 I
b11111111 G
1$
b10010000101010011010100100100 H
0L
b1111 M
1N
b10010000101010011010100100100 /
b10010000101010011010100100100 9
b1 0
1.
#120
0.
#125
b11000000100010010101111010000001 ,
b11000000100010010101111010000001 I
b1001000010101001101010010010011000000100010010101111010000001 H
b10 0
b11000000100010010101111010000001 /
b11000000100010010101111010000001 9
b10010000101010011010100100100 J
1N
1.
#130
0.
#135
b10000100100001001101011000001001 ,
b10000100100001001101011000001001 I
b1100000010001001010111101000000110000100100001001101011000001001 H
b11000000100010010101111010000001 J
1N
b10000100100001001101011000001001 /
b10000100100001001101011000001001 9
1(
b11 0
1.
#140
0.
#145
b0 )
b0 F
0;
0!
1<
1"
b10110001111100000101011001100011 ,
b10110001111100000101011001100011 I
b11110000 G
0&
1%
b1000010010000100110101100000100110110001111100000101011001100011 H
0>
1'
0(
b0 0
b10110001111100000101011001100011 /
b10110001111100000101011001100011 9
b10000100100001001101011000001001 J
1N
1K
1.
#150
0.
#155
0<
0"
1;
1!
0%
b1101101100011111000001010110 ,
b1101101100011111000001010110 I
b11010111001011110110000110110110001111100000101011001100011 H
b11111 G
1&
1>
0'
b1000 C
b1111 )
b1111 F
b1000 D
b11 E
1L
0K
0N
b1 *
b1 @
b1 B
b1 -
b1 7
b110101110010111101100001101 1
b110101110010111101100001101 :
1.
#160
0.
#165
b1100011010001101101111110011001 ,
b1100011010001101101111110011001 I
1=
1#
b1011000111110000010101100110001101000110110111111001100110001101 H
b11111111 G
1$
b1 0
b1000110110111111001100110001101 /
b1000110110111111001100110001101 9
b10110001111100000101011001100011 J
1N
0L
1.
#170
0.
#175
b10001101101100101100001010000100 ,
b10001101101100101100001010000100 I
b100011011011111100110011000110110110010110000101000010001100101 H
b1000110110111111001100110001101 J
1N
b10110010110000101000010001100101 /
b10110010110000101000010001100101 9
b10 0
1.
#180
0.
#185
b1100101100010010011011101010010 ,
b1100101100010010011011101010010 I
b1011001011000010100001000110010110001001001101110101001000010010 H
1(
b11 0
b10001001001101110101001000010010 /
b10001001001101110101001000010010 9
b10110010110000101000010001100101 J
1N
1.
#190
0.
#195
b1000 )
b1000 F
0;
0!
1<
1"
b11110000 G
0&
1%
b10010000000001111001111100011 ,
b10010000000001111001111100011 I
0>
1'
b1000100100110111010100100001001000000000111100111110001100000001 H
1K
b10001001001101110101001000010010 J
1N
b111100111110001100000001 /
b111100111110001100000001 9
0(
b0 0
1.
#200
0.
#205
0<
0"
0%
b11001101000011010000000011110011 ,
b11001101000011010000000011110011 I
1;
1!
b10000 C
b1111 )
b1111 F
b1100 D
b10 E
1>
0'
b11011010111110011010000110100000000111100111110001100000001 H
b111111 G
1&
b11 *
b11 @
b10 B
b10 -
b10 7
b110110101111100110100001101 1
b110110101111100110100001101 :
0N
0K
1L
1.
#210
0.
#215
1=
1#
b11100011000000010011101100100011 ,
b11100011000000010011101100100011 I
b11111111 G
1$
b11110011111000110000000100111011001000111111000101110110 H
0L
b111100111110001100000001 J
1N
b111011001000111111000101110110 /
b111011001000111111000101110110 9
b1 0
1.
#220
0.
#225
b11110001011101100001111010001101 ,
b11110001011101100001111010001101 I
b11101100100011111100010111011000011110100011011100110100111101 H
b10 0
b11110100011011100110100111101 /
b11110100011011100110100111101 9
b111011001000111111000101110110 J
1N
1.
#230
0.
#235
b11001101001111010111011011010100 ,
b11001101001111010111011011010100 I
b1111010001101110011010011110101110110110101000101011111101101 H
b11110100011011100110100111101 J
1N
b1110110110101000101011111101101 /
b1110110110101000101011111101101 9
1(
b11 0
1.
#240
0.
#245
b1100 )
b1100 F
0;
0!
1<
1"
b1010111111011010100011000101101 ,
b1010111111011010100011000101101 I
b11110000 G
0&
1%
b111011011010100010101111110110101000110001011011111011110001100 H
0>
1'
0(
b0 0
b1000110001011011111011110001100 /
b1000110001011011111011110001100 9
b1110110110101000101011111101101 J
1N
1K
1.
#250
0.
#255
0<
0"
1;
1!
0%
b11111101111010011111100101000110 ,
b11111101111010011111100101000110 I
b111110011111101111010011111100101000110001011011111011110001100 H
b111111 G
1&
1>
0'
b11000 C
b111 )
b111 F
b1110 D
b1 E
1L
0K
0N
b11 B
b11 -
b11 7
b1111100111111011110100111111001 1
b1111100111111011110100111111001 :
1.
#260
0.
#265
b101101111101111000110011100011 ,
b101101111101111000110011100011 I
b1111 )
b1111 F
1=
1#
b100011000101101111101111000110011100011001101110010010011000110 H
b11111111 G
1$
b1 0
b11100011001101110010010011000110 /
b11100011001101110010010011000110 9
b1000110001011011111011110001100 J
1N
0L
1.
#270
0.
#275
b110111001001001100011011100010 ,
b110111001001001100011011100010 I
b1110001100110111001001001100011011100010111101111000010011000101 H
b11100011001101110010010011000110 J
1N
b11100010111101111000010011000101 /
b11100010111101111000010011000101 9
b10 0
1.
#280
0.
#285
b11110111100001001100010111010101 ,
b11110111100001001100010111010101 I
b1110001011110111100001001100010111010101000100111101001010101010 H
1(
b11 0
b11010101000100111101001010101010 /
b11010101000100111101001010101010 9
b11100010111101111000010011000101 J
1N
1.
#290
0.
#295
b1110 )
b1110 F
0;
0!
1<
1"
b11110000 G
0&
1%
b10011110100101010101001110010 ,
b10011110100101010101001110010 I
0>
1'
b1101010100010011110100101010101001110010101011111111011111100101 H
1K
b11010101000100111101001010101010 J
1N
b1110010101011111111011111100101 /
b1110010101011111111011111100101 9
0(
b0 0
1.
#300
0.
#305
0<
0"
0%
b1110010101011111111011111100101 ,
b1110010101011111111011111100101 I
1;
1!
b0 C
b1111 )
b1111 F
b1111 D
b0 E
1>
0'
b1011101111010010011100100111011101110010101011111111011111100101 H
b1111 G
1&
b1 2
b0 *
b0 @
b0 B
b0 -
b0 7
b10111011110100100111001001110111 1
b10111011110100100111001001110111 :
0N
0K
1L
1.
#310
0.
#315
1=
1#
b10001001001100101101011000010010 ,
b10001001001100101101011000010010 I
b11111111 G
1$
b111001010101111111101111110010110001001001100101101011000010010 H
0L
b1110010101011111111011111100101 J
1N
b10001001001100101101011000010010 /
b10001001001100101101011000010010 9
b1 0
1.
#320
0.
#325
b1000111111011001101101110001111 ,
b1000111111011001101101110001111 I
b1000100100110010110101100001001001000111111011001101101110001111 H
b10 0
b1000111111011001101101110001111 /
b1000111111011001101101110001111 9
b10001001001100101101011000010010 J
1N
1.
#330
0.
#335
b1110 )
b1110 F
b11111110 G
b1111001001100000110100111110010 ,
b1111001001100000110100111110010 I
b100011111101100110110111000111101111001001100000110100111110010 H
b1110 D
b1110 +
b1110 ?
b1000111111011001101101110001111 J
1N
b1111001001100000110100111110010 /
b1111001001100000110100111110010 9
1(
b11 0
1.
#340
0.
#345
b0 )
b0 F
0;
0!
1<
1"
b11100111011101101001011011001110 ,
b11100111011101101001011011001110 I
b11100000 G
0&
1%
b1111 D
b1111 +
b1111 ?
b111100100110000011010011111001011100111011101101001011011001110 H
0>
1'
0(
b0 0
b11100111011101101001011011001110 /
b11100111011101101001011011001110 9
b1110 M
b1111001001100000110100111110010 J
1N
1K
1.
#350
0.
#355
0<
0"
b1111 )
b1111 F
1;
1!
0%
b11101000111001110111011010010110 ,
b11101000111001110111011010010110 I
b1111010000000000011110101110100011100111011101101001011011001110 H
b11111 G
1&
1>
0'
b1000 C
b1000 D
b11 E
1L
0K
0N
b1 *
b1 @
b1 B
b1 -
b1 7
b11110100000000000111101011101000 1
b11110100000000000111101011101000 :
1.
#360
0.
#365
b11001110111000101100101001001110 ,
b11001110111000101100101001001110 I
b1111 )
b1111 F
1=
1#
b1110011101110110100101101100111011100010110010100100111011000101 H
b11111111 G
1$
b1 0
b11100010110010100100111011000101 /
b11100010110010100100111011000101 9
b1111 M
b11100111011101101001011011001110 J
1N
0L
1.
#370
0.
#375
b11000101001011100101100001001001 ,
b11000101001011100101100001001001 I
b1110001011001010010011101100010100101110010110000100100101011100 H
b11100010110010100100111011000101 J
1N
b101110010110000100100101011100 /
b101110010110000100100101011100 9
b10 0
1.
#380
0.
#385
1<
1"
1%
1'
b11111110 G
0>
b1011100110111101000111000101000 ,
b1011100110111101000111000101000 I
b0 D
b1110 +
b1110 ?
b10111001011000010010010101110011011110100011100010100010111101 H
1(
b11 0
b11011110100011100010100010111101 /
b11011110100011100010100010111101 9
b101110010110000100100101011100 J
1N
1.
#390
0.
#395
0<
0"
0%
0'
b1011000001011011011001010100111 ,
b1011000001011011011001010100111 I
1>
b111111 G
b1001011010101011010110000010110110110010101001110010011001100101 H
b1111 +
b1111 ?
b10000 C
b1100 D
b10 E
1L
b1110 M
b11011110100011100010100010111101 J
1N
b10110010101001110010011001100101 /
b10110010101001110010011001100101 9
0(
b0 0
b11 *
b11 @
b10 B
b10 -
b10 7
b10010110101010110101100000101101 1
b10010110101010110101100000101101 :
1.
#400
0.
#405
b100110011001011011000111101111 ,
b100110011001011011000111101111 I
b1111 )
b1111 F
b1011001010100111001001100110010110110001111011110110001001100011 H
b11111111 G
b1 0
b10110001111011110110001001100011 /
b10110001111011110110001001100011 9
b1111 M
b10110010101001110010011001100101 J
1N
0L
1.
#410
0.
#415
b1100010011000110000010101110011 ,
b1100010011000110000010101110011 I
b1011000111101111011000100110001100000101011100111000011100001010 H
b10110001111011110110001001100011 J
1N
b101011100111000011100001010 /
b101011100111000011100001010 9
b10 0
1.
#420
0.
#425
b11111110 G
b10000111000010101100000000111011 ,
b10000111000010101100000000111011 I
b1000 D
b1110 +
b1110 ?
b10101110011100001110000101011000000001110110010001010000000 H
1(
b11 0
b11000000001110110010001010000000 /
b11000000001110110010001010000000 9
b101011100111000011100001010 J
1N
1.
#430
0.
#435
0;
0!
1<
1"
b1000 )
b1000 F
0&
1%
b11100000 G
b100010100000000001000001100100 ,
b100010100000000001000001100100 I
0>
1'
b1100000000111011001000101000000000010000011001000010000100100000 H
b1100 D
b1111 +
b1111 ?
1K
b1110 M
b11000000001110110010001010000000 J
1N
b10000011001000010000100100000 /
b10000011001000010000100100000 9
0(
b0 0
1.
#440
0.
#445
0<
0"
0%
b1111000010001011010101000010000 ,
b1111000010001011010101000010000 I
1;
1!
b11000 C
b111 )
b111 F
b1110 D
b1 E
1>
0'
b101010101111000010001011010101000010000011001000010000100100000 H
b111111 G
1&
b11 B
b11 -
b11 7
b1010101011110000100010110101010 1
b1010101011110000100010110101010 :
0N
0K
1L
1.
#450
0.
#455
b1111 )
b1111 F
1=
1#
b1100100001000010010000011001110 ,
b1100100001000010010000011001110 I
b11111111 G
1$
b1000001100100001000010010000011001110110011001100110010011101 H
0L
b1111 M
b10000011001000010000100100000 J
1N
b11001110110011001100110010011101 /
b11001110110011001100110010011101 9
b1 0
1.
#460
0.
#465
b11001100110011001001110111001011 ,
b11001100110011001001110111001011 I
b1100111011001100110011001001110111001011001000000011111010010110 H
b10 0
b11001011001000000011111010010110 /
b11001011001000000011111010010110 9
b11001110110011001100110010011101 J
1N
1.
#470
0.
#475
b11111110 G
b100000001111101001011010001001 ,
b100000001111101001011010001001 I
b1100101100100000001111101001011010001001100000111011100000010011 H
b1100 D
b1110 +
b1110 ?
b11001011001000000011111010010110 J
1N
b10001001100000111011100000010011 /
b10001001100000111011100000010011 9
1(
b11 0
1.
#480
0.
#485
b1100 )
b1100 F
0;
0!
1<
1"
b10000011101110000001001110000110 ,
b10000011101110000001001110000110 I
b11100000 G
0&
1%
b1110 D
b1111 +
b1111 ?
b1000100110000011101110000001001110000110101111000011100000001101 H
0>
1'
0(
b0 0
b10000110101111000011100000001101 /
b10000110101111000011100000001101 9
b1110 M
b10001001100000111011100000010011 J
1N
1K
1.
#490
0.
#495
0<
0"
1;
1!
0%
b10000110101111000011100000001101 ,
b10000110101111000011100000001101 I
b1010100110100111110101100101001110000110101111000011100000001101 H
b1111 G
1&
1>
0'
b0 C
b1111 )
b1111 F
b1111 D
b0 E
1L
0K
0N
b10 2
b0 *
b0 @
b0 B
b0 -
b0 7
b10101001101001111101011001010011 1
b10101001101001111101011001010011 :
1.
#500
0.
#505
b110101100111111101110101101011 ,
b110101100111111101110101101011 I
1=
1#
b1000011010111100001110000000110100110101100111111101110101101011 H
b11111111 G
1$
b1 0
b110101100111111101110101101011 /
b110101100111111101110101101011 9
b1111 M
b10000110101111000011100000001101 J
1N
0L
1.
#510
0.
#515
b11101010101001100010101011010101 ,
b11101010101001100010101011010101 I
b11010110011111110111010110101111101010101001100010101011010101 H
b110101100111111101110101101011 J
1N
b11101010101001100010101011010101 /
b11101010101001100010101011010101 9
b10 0
1.
#520
0.
#525
b1100 )
b1100 F
b11111100 G
b10000001000101110100101000000010 ,
b10000001000101110100101000000010 I
b1100 D
b1100 +
b1100 ?
b1110101010100110001010101101010110000001000101110100101000000010 H
1(
b11 0
b10000001000101110100101000000010 /
b10000001000101110100101000000010 9
b11101010101001100010101011010101 J
1N
1.
#530
0.
#535
0;
0!
1<
1"
b0 )
b0 F
0&
1%
b11000000 G
b11010111010101100011111010101110 ,
b11010111010101100011111010101110 I
0>
1'
b1000000100010111010010100000001011010111010101100011111010101110 H
b1111 D
b1111 +
b1111 ?
1K
b1100 M
b10000001000101110100101000000010 J
1N
b11010111010101100011111010101110 /
b11010111010101100011111010101110 9
0(
b0 0
1.
#540
0.
#545
0<
0"
b11101110101110101011000111110 ,
b11101110101110101011000111110 I
0%
b1111 )
b1111 F
1;
1!
b1000 C
b1000 D
b11 E
1>
0'
b111011111111111010010001110111010111010101100011111010101110 H
b11111 G
1&
b1 *
b1 @
b1 B
b1 -
b1 7
b1110111111111110100100011101 1
b1110111111111110100100011101 :
0N
0K
1L
1.
#550
0.
#555
1=
1#
b10101110111001111100010101110010 ,
b10101110111001111100010101110010 I
b11111111 G
1$
b1101011101010110001111101010111011100111110001010111001011001111 H
0L
b1111 M
b11010111010101100011111010101110 J
1N
b11100111110001010111001011001111 /
b11100111110001010111001011001111 9
b1 0
1.
#560
0.
#565
b11001111000100011000010001001001 ,
b11001111000100011000010001001001 I
b1110011111000101011100101100111100010001100001000100100100100011 H
b10 0
b10001100001000100100100100011 /
b10001100001000100100100100011 9
b11100111110001010111001011001111 J
1N
1.
#570
0.
#575
1<
1"
1%
b1110 )
b1110 F
1'
b11111100 G
b100011000001010000100101100101 ,
b100011000001010000100101100101 I
0>
b1000110000100010010010010001100000101000010010110010100001010 H
b0 D
b1100 +
b1100 ?
b10001100001000100100100100011 J
1N
b101000010010110010100001010 /
b101000010010110010100001010 9
1(
b11 0
1.
#580
0.
#585
0<
0"
0%
0'
1>
b1001100001111001110010101110011 ,
b1001100001111001110010101110011 I
b10000 C
b1111 )
b1111 F
b10 E
b1100 D
b1111 +
b1111 ?
b1001111000110001010011000011110011100101011100110000101011001010 H
b111111 G
b11 *
b11 @
b10 B
b10 -
b10 7
b10011110001100010100110000111100 1
b10011110001100010100110000111100 :
0(
b0 0
b11100101011100110000101011001010 /
b11100101011100110000101011001010 9
b1100 M
b101000010010110010100001010 J
1N
1L
1.
#590
0.
#595
b1010110010100111100101101000 ,
b1010110010100111100101101000 I
b11111111 G
b1110010101110011000010101100101001111001011010001011110111110010 H
0L
b1111 M
b11100101011100110000101011001010 J
1N
b1111001011010001011110111110010 /
b1111001011010001011110111110010 9
b1 0
1.
#600
0.
#605
b10111101111100100100010100101110 ,
b10111101111100100100010100101110 I
b111100101101000101111011111001001000101001011100110000110001010 H
b10 0
b1000101001011100110000110001010 /
b1000101001011100110000110001010 9
b1111001011010001011110111110010 J
1N
1.
#610
0.
#615
1<
1"
1%
1'
b11111100 G
b1100001100010100010000011000100 ,
b1100001100010100010000011000100 I
0>
b100010100101110011000011000101000100000110001001011001101000001 H
b0 D
b1100 +
b1100 ?
b1000101001011100110000110001010 J
1N
b100000110001001011001101000001 /
b100000110001001011001101000001 9
1(
b11 0
1.
#620
0.
#625
0<
0"
0%
0'
1>
b100000111100110111100011101100 ,
b100000111100110111100011101100 I
b111 )
b111 F
b11000 C
b1 E
b1110 D
b1111 +
b1111 ?
b11110000100000111100110111100011101100010010110011010011011000 H
b111111 G
b11 B
b11 -
b11 7
b111100001000001111001101111000 1
b111100001000001111001101111000 :
0(
b0 0
b11101100010010110011010011011000 /
b11101100010010110011010011011000 9
b1100 M
b100000110001001011001101000001 J
1N
1L
1.
#630
0.
#635
b1111 )
b1111 F
b1001011001101001101100011000100 ,
b1001011001101001101100011000100 I
b11111111 G
b1110110001001011001101001101100011000100100010100001001010001001 H
0L
b1111 M
b11101100010010110011010011011000 J
1N
b11000100100010100001001010001001 /
b11000100100010100001001010001001 9
b1 0
1.
#640
0.
#645
b10001010000100101000100101110101 ,
b10001010000100101000100101110101 I
b1100010010001010000100101000100101110101110001010000110111101011 H
b10 0
b1110101110001010000110111101011 /
b1110101110001010000110111101011 9
b11000100100010100001001010001001 J
1N
1.
#650
0.
#655
b11111100 G
b11000101000011011110101101011011 ,
b11000101000011011110101101011011 I
b111010111000101000011011110101101011011000000100110010110110110 H
b1000 D
b1100 +
b1100 ?
b1110101110001010000110111101011 J
1N
b1011011000000100110010110110110 /
b1011011000000100110010110110110 9
1(
b11 0
1.
#660
0.
#665
b1000 )
b1000 F
0;
0!
1<
1"
b10011001011011011001100011 ,
b10011001011011011001100011 I
b11000000 G
0&
1%
b1110 D
b1111 +
b1111 ?
b101101100000010011001011011011001100011010010111111100111000110 H
0>
1'
0(
b0 0
b1100011010010111111100111000110 /
b1100011010010111111100111000110 9
b1100 M
b1011011000000100110010110110110 J
1N
1K
1.
#670
0.
#675
0<
0"
1;
1!
0%
b1100011010010111111100111000110 ,
b1100011010010111111100111000110 I
b101011100010101000100111010111001100011010010111111100111000110 H
b1111 G
1&
1>
0'
b0 C
b1111 )
b1111 F
b1111 D
b0 E
1L
0K
0N
b11 2
b0 *
b0 @
b0 B
b0 -
b0 7
b1010111000101010001001110101110 1
b1010111000101010001001110101110 :
1.
#680
0.
#685
b11011110011101010000001010111100 ,
b11011110011101010000001010111100 I
1=
1#
b110001101001011111110011100011011011110011101010000001010111100 H
b11111111 G
1$
b1 0
b11011110011101010000001010111100 /
b11011110011101010000001010111100 9
b1111 M
b1100011010010111111100111000110 J
1N
0L
1.
#690
0.
#695
b10101000011111101110100101010 ,
b10101000011111101110100101010 I
b1101111001110101000000101011110000010101000011111101110100101010 H
b11011110011101010000001010111100 J
1N
b10101000011111101110100101010 /
b10101000011111101110100101010 9
b10 0
1.
#700
0.
